ketchup/__init__.py
ketchup/cli.py
ketchup/ketchup.py
ketchup-0.1.1.dist-info/entry_points.txt
ketchup-0.1.1.dist-info/LICENSE
ketchup-0.1.1.dist-info/WHEEL
ketchup-0.1.1.dist-info/METADATA
ketchup-0.1.1.dist-info/RECORD
